Workbook

Sheet GFS Entry
A1: Ledger* | B1: Amount Class* | C1: Entity* | D1: Account Sub - Account* | E1: Center* | F1: Office Location* | G1: Product Sub - Product* | H1: Affiliate* | I1: Txn ccy | J1: Trans Amount | K1: Func ccy | L1: Func Amount | M1: Rep ccy | N1: Rep Amount | O1: FX Rate (TXN2FUNC) | P1: FX Rate (TXN2REP) | Q1: SL Journal Line Description | R1: Statistical Amount | S1: Block-of-Business | T1: Client | U1: Reinsurer | V1: Risk Location | W1: Obligor | X1: Accident Year | Y1: Agreement | Z1: Catastrophe Loss Indicator | AA1: Catastrophe Code | AB1: Marketing Channel | AC1: Program Code | AD1: Pay Code | AE1: Code Type | AF1: Covered Equipment | AG1: Underwriting Year | AH1: Dealer Group Number | AI1: Dealer Number | AJ1: Dealer State | AK1: Insured State | AL1: Policy Number
A2: USD Functional | B2: Cash | C2: E01300 | D2: A700018-00 | E2: C200593 | F2: L0001 | G2: P0000-000 | H2: E00000 | I2: USD | J2: =-Allocation!I10 -> -8646841.1 | Q2: Spread Group Ins. By FTE 10/2025
A3: USD Functional | B3: Cash | C3: E01300 | D3: A700018-00 | E3: C200593 | F3: L0001 | G3: P0000-000 | H3: E00330 | I3: USD | J3: =-Allocation!I9 -> -28628.794 | Q3: Spread Group Ins. By FTE 10/2025
A4: USD Functional | B4: Cash | C4: E00330 | D4: A700018-00 | E4: C040414 | F4: L0001 | G4: P0000-000 | H4: E01300 | I4: USD | J4: 285.1456 | Q4: Spread Group Ins. By FTE 10/2025
A5: USD Functional | B5: Cash | C5: E01300 | D5: A700018-00 | E5: C010000 | F5: L0001 | G5: P0000-000 | H5: E00000 | I5: USD | J5: 5520.6774 | Q5: Spread Group Ins. By FTE 10/2025
A6: USD Functional | B6: Cash | C6: E01300 | D6: A700018-00 | E6: C010011 | F6: L0001 | G6: P0000-000 | H6: E00000 | I6: USD | J6: 802.96389 | Q6: Spread Group Ins. By FTE 10/2025
A7: USD Functional | B7: Cash | C7: E01300 | D7: A700018-00 | E7: C010101 | F7: L0001 | G7: P0000-000 | H7: E00000 | I7: USD | J7: 10477.008 | Q7: Spread Group Ins. By FTE 10/2025
A8: USD Functional | B8: Cash | C8: E01300 | D8: A700018-00 | E8: C010105 | F8: L0001 | G8: P0000-000 | H8: E00000 | I8: USD | J8: 8264.6339 | Q8: Spread Group Ins. By FTE 10/2025
A9: USD Functional | B9: Cash | C9: E01300 | D9: A700018-00 | E9: C010110 | F9: L0001 | G9: P0000-000 | H9: E00000 | I9: USD | J9: 2712.9732 | Q9: Spread Group Ins. By FTE 10/2025
A10: USD Functional | B10: Cash | C10: E01300 | D10: A700018-00 | E10: C010111 | F10: L0001 | G10: P0000-000 | H10: E00000 | I10: USD | J10: 5686.7714 | Q10: Spread Group Ins. By FTE 10/2025
A11: USD Functional | B11: Cash | C11: E01300 | D11: A700018-00 | E11: C010115 | F11: L0001 | G11: P0000-000 | H11: E00000 | I11: USD | J11: 5762.7926 | Q11: Spread Group Ins. By FTE 10/2025
A12: USD Functional | B12: Cash | C12: E01300 | D12: A700018-00 | E12: C010121 | F12: L0001 | G12: P0000-000 | H12: E00000 | I12: USD | J12: 4818.8518 | Q12: Spread Group Ins. By FTE 10/2025
A13: USD Functional | B13: Cash | C13: E01300 | D13: A700018-00 | E13: C010122 | F13: L0001 | G13: P0000-000 | H13: E00000 | I13: USD | J13: 16824.506 | Q13: Spread Group Ins. By FTE 10/2025
A14: USD Functional | B14: Cash | C14: E01300 | D14: A700018-00 | E14: C010124 | F14: L0001 | G14: P0000-000 | H14: E00000 | I14: USD | J14: 6416.1809 | Q14: Spread Group Ins. By FTE 10/2025
A15: USD Functional | B15: Cash | C15: E01300 | D15: A700018-00 | E15: C010127 | F15: L0001 | G15: P0000-000 | H15: E00000 | I15: USD | J15: 6279.5458 | Q15: Spread Group Ins. By FTE 10/2025
... A709: USD Functional | B709: Cash | C709: E01300 | D709: A700018-00 | E709: C515008 | F709: L0001 | G709: P0000-000 | H709: E00000 | I709: USD | J709: 1054.8229 | Q709: Spread Group Ins. By FTE 10/2025

Sheet Allocation
C3: Entity | D3: Cost Center | E3: Amount
C4: E00330 | D4: C040414 | E4: 285.1456
C5: E01300 | D5: C010000 | E5: 5520.6774
C6: E01300 | D6: C010011 | E6: 802.96389
C7: E01300 | D7: C010101 | E7: 10477.008
C8: E01300 | D8: C010105 | E8: 8264.6339 | H8: Row Labels | I8: Sum of Amount
C9: E01300 | D9: C010110 | E9: 2712.9732 | H9: E00330 | I9: 28628.794
C10: E01300 | D10: C010111 | E10: 5686.7714 | H10: E01300 | I10: 8646841.1
C11: E01300 | D11: C010115 | E11: 5762.7926 | H11: Grand Total | I11: 8675469.9
C12: E01300 | D12: C010121 | E12: 4818.8518
C13: E01300 | D13: C010122 | E13: 16824.506
C14: E01300 | D14: C010124 | E14: 6416.1809
C15: E01300 | D15: C010127 | E15: 6279.5458
C16: E01300 | D16: C010150 | E16: 4506.3536
C17: E01300 | D17: C010205 | E17: 3027.9537
C18: E01300 | D18: C010210 | E18: 12755.259
C19: E01300 | D19: C010215 | E19: 13752.606
C20: E01300 | D20: C010220 | E20: 14829.946
C21: E01300 | D21: C010230 | E21: 14758.68
C22: E01300 | D22: C010301 | E22: 9801.7422
C23: E01300 | D23: C010305 | E23: 12111.828
... C709: E01300 | D709: C515008 | E709: 1054.8229

Sheet Cash Calc.
A2: Row Labels | B2: Sum of FTE | C2: Health & Welfare Expense | D2: Cost/FTE | E2: Segment H&W
A3: Corporate | B3: 2421 | E3: =B3*$D$6 -> 2059754.1 | F3: =GETPIVOTDATA("FTE",$A$2,"Segment","Corporate")/GETPIVOTDATA("FTE",$A$2) -> 0.23742277
A4: Housing | B4: 4318 | E4: =B4*$D$6 -> 3673696.1 | F4: =GETPIVOTDATA("FTE",$A$2,"Segment","Housing")/GETPIVOTDATA("FTE",$A$2) -> 0.42345788
A5: Lifestyle | B5: 3458 | E5: =B5*$D$6 -> 2942019.7 | F5: =GETPIVOTDATA("FTE",$A$2,"Segment","Lifestyle")/GETPIVOTDATA("FTE",$A$2) -> 0.33911935
A6: Grand Total | B6: 10197 | C6: ='GFS Cube'!C14 -> 8675469.9 | D6: =C6/GETPIVOTDATA("FTE",$A$2) -> 850.78649 | E6: =SUM(E3:E5) -> 8675469.9
A8: Segment | B8: Corporate | H8: Segment | I8: Housing | O8: Segment | P8: Lifestyle
A10: Sum of Salary | H10: Sum of Salary | O10: Sum of Salary
A11: Entity_Code | B11: Center_Code | C11: Total | D11: % of Salary | E11: H&W per CC | F11: Load Rate | H11: Entity_Code | I11: Center_Code | J11: Total | K11: % of Salary | L11: H&W per CC | M11: Load Rate | O11: Entity_Code | P11: Center_Code | Q11: Total | R11: % of Salary | S11: H&W per CC | T11: Load Rate
A12: E00330 | B12: C040414 | C12: 1676 | D12: =C12/$C$282 -> 0.00013843672 | E12: =D12*$E$3 -> 285.1456 | F12: =E12/C12 -> 0.17013461 | H12: E00330 | I12: C301007 | J12: 3576.92 | K12: =J12/$J$216 -> 0.00037666482 | L12: =K12*$E$4 -> 1383.7521 | M12: =L12/J12 -> 0.38685575 | O12: E01300 | P12: C010155 | Q12: 25526.54 | R12: =Q12/$Q$244 -> 0.0027994999 | S12: =R12*$E$5 -> 8236.1838 | T12: =S12/Q12 -> 0.32265179
A13: E01300 | B13: C010000 | C13: 32448.88 | D13: =C13/$C$282 -> 0.0026802604 | E13: =D13*$E$3 -> 5520.6774 | F13: =E13/C13 -> 0.17013461 | H13: E00330 | I13: C301008 | J13: 4769.23 | K13: =J13/$J$216 -> 0.00050222011 | L13: =K13*$E$4 -> 1845.0041 | M13: =L13/J13 -> 0.38685575 | O13: E01300 | P13: C010160 | Q13: 49363.46 | R13: =Q13/$Q$244 -> 0.0054136989 | S13: =R13*$E$5 -> 15927.209 | T13: =S13/Q13 -> 0.32265179
A14: E01300 | B14: C010011 | C14: 4719.58 | D14: =C14/$C$282 -> 0.00038983483 | E14: =D14*$E$3 -> 802.96389 | F14: =E14/C14 -> 0.17013461 | H14: E00330 | I14: C350102 | J14: 4876.65 | K14: =J14/$J$216 -> 0.00051353189 | L14: =K14*$E$4 -> 1886.5601 | M14: =L14/J14 -> 0.38685575 | O14: E01300 | P14: C010162 | Q14: 92640.3 | R14: =Q14/$Q$244 -> 0.010159877 | S14: =R14*$E$5 -> 29890.559 | T14: =S14/Q14 -> 0.32265179
A15: E01300 | B15: C010101 | C15: 61580.7 | D15: =C15/$C$282 -> 0.0050865335 | E15: =D15*$E$3 -> 10477.008 | F15: =E15/C15 -> 0.17013461 | H15: E00330 | I15: C350103 | J15: 7224.19 | K15: =J15/$J$216 -> 0.00076073779 | L15: =K15*$E$4 -> 2794.7194 | M15: =L15/J15 -> 0.38685575 | O15: E01300 | P15: C010163 | Q15: 47526.69 | R15: =Q15/$Q$244 -> 0.00521226 | S15: =R15*$E$5 -> 15334.572 | T15: =S15/Q15 -> 0.32265179
A16: E01300 | B16: C010105 | C16: 48577.03 | D16: =C16/$C$282 -> 0.0040124372 | E16: =D16*$E$3 -> 8264.6339 | F16: =E16/C16 -> 0.17013461 | H16: E00330 | I16: C350106 | J16: 3556.88 | K16: =J16/$J$216 -> 0.00037455452 | L16: =K16*$E$4 -> 1375.9995 | M16: =L16/J16 -> 0.38685575 | O16: E01300 | P16: C010164 | Q16: 179021.21 | R16: =Q16/$Q$244 -> 0.019633286 | S16: =R16*$E$5 -> 57761.514 | T16: =S16/Q16 -> 0.32265179
A17: E01300 | B17: C010110 | C17: 15946.04 | D17: =C17/$C$282 -> 0.0013171345 | E17: =D17*$E$3 -> 2712.9732 | F17: =E17/C17 -> 0.17013461 | H17: E00330 | I17: C350110 | J17: 10415.43 | K17: =J17/$J$216 -> 0.0010967889 | L17: =K17*$E$4 -> 4029.269 | M17: =L17/J17 -> 0.38685575 | O17: E01300 | P17: C010180 | Q17: 34692.52 | R17: =Q17/$Q$244 -> 0.0038047344 | S17: =R17*$E$5 -> 11193.604 | T17: =S17/Q17 -> 0.32265179
A18: E01300 | B18: C010111 | C18: 33425.13 | D18: =C18/$C$282 -> 0.0027608982 | E18: =D18*$E$3 -> 5686.7714 | F18: =E18/C18 -> 0.17013461 | H18: E00330 | I18: C350512 | J18: 2178.72 | K18: =J18/$J$216 -> 0.00022942844 | L18: =K18*$E$4 -> 842.85036 | M18: =L18/J18 -> 0.38685575 | O18: E01300 | P18: C010450 | Q18: 58345.65 | R18: =Q18/$Q$244 -> 0.0063987772 | S18: =R18*$E$5 -> 18825.328 | T18: =S18/Q18 -> 0.32265179
A19: E01300 | B19: C010115 | C19: 33871.96 | D19: =C19/$C$282 -> 0.0027978061 | E19: =D19*$E$3 -> 5762.7926 | F19: =E19/C19 -> 0.17013461 | H19: E00330 | I19: C350520 | J19: 1920.9 | K19: =J19/$J$216 -> 0.0002022789 | L19: =K19*$E$4 -> 743.11121 | M19: =L19/J19 -> 0.38685575 | O19: E01300 | P19: C010451 | Q19: 49717.2 | R19: =Q19/$Q$244 -> 0.0054524936 | S19: =R19*$E$5 -> 16041.344 | T19: =S19/Q19 -> 0.32265179
A20: E01300 | B20: C010121 | C20: 28323.76 | D20: =C20/$C$282 -> 0.0023395277 | E20: =D20*$E$3 -> 4818.8518 | F20: =E20/C20 -> 0.17013461 | H20: E00330 | I20: C350527 | J20: 1838.16 | K20: =J20/$J$216 -> 0.00019356603 | L20: =K20*$E$4 -> 711.10277 | M20: =L20/J20 -> 0.38685575 | O20: E01300 | P20: C010452 | Q20: 87773.73 | R20: =Q20/$Q$244 -> 0.0096261596 | S20: =R20*$E$5 -> 28320.351 | T20: =S20/Q20 -> 0.32265179
A21: E01300 | B21: C010122 | C21: 98889.38 | D21: =C21/$C$282 -> 0.0081682109 | E21: =D21*$E$3 -> 16824.506 | F21: =E21/C21 -> 0.17013461 | H21: E00330 | I21: C350529 | J21: 5145.18 | K21: =J21/$J$216 -> 0.00054180924 | L21: =K21*$E$4 -> 1990.4425 | M21: =L21/J21 -> 0.38685575 | O21: E01300 | P21: C010453 | Q21: 10748.96 | R21: =Q21/$Q$244 -> 0.0011788402 | S21: =R21*$E$5 -> 3468.1712 | T21: =S21/Q21 -> 0.32265179
A22: E01300 | B22: C010124 | C22: 37712.38 | D22: =C22/$C$282 -> 0.0031150228 | E22: =D22*$E$3 -> 6416.1809 | F22: =E22/C22 -> 0.17013461 | H22: E00330 | I22: C350553 | J22: 4440.77 | K22: =J22/$J$216 -> 0.00046763188 | L22: =K22*$E$4 -> 1717.9374 | M22: =L22/J22 -> 0.38685575 | O22: E01300 | P22: C303058 | Q22: 13673.24 | R22: =Q22/$Q$244 -> 0.0014995465 | S22: =R22*$E$5 -> 4411.6954 | T22: =S22/Q22 -> 0.32265179
A23: E01300 | B23: C010127 | C23: 36909.28 | D23: =C23/$C$282 -> 0.0030486871 | E23: =D23*$E$3 -> 6279.5458 | F23: =E23/C23 -> 0.17013461 | H23: E00330 | I23: C350557 | J23: 2737.6 | K23: =J23/$J$216 -> 0.00028828087 | L23: =K23*$E$4 -> 1059.0563 | M23: =L23/J23 -> 0.38685575 | O23: E01300 | P23: C380000 | Q23: 110052.64 | R23: =Q23/$Q$244 -> 0.012069491 | S23: =R23*$E$5 -> 35508.681 | T23: =S23/Q23 -> 0.32265179
... A215: E01300 | B215: C252121 | C215: 51350.42 | D215: =C215/$C$282 -> 0.0042415177 | E215: =D215*$E$3 -> 8736.4835 | F215: =E215/C215 -> 0.17013461 | H215: E01300 | I215: C350726 | J215: 5006.62 | K215: =J215/$J$216 -> 0.00052721828 | L215: =K215*$E$4 -> 1936.8397 | M215: =L215/J215 -> 0.38685575 | O215: E01300 | P215: C385008 | Q215: 37639.08 | R215: =Q215/$Q$244 -> 0.0041278842 | S215: =R215*$E$5 -> 12144.317 | T215: =S215/Q215 -> 0.32265179
A216: E01300 | B216: C252124 | C216: 39442.97 | D216: =C216/$C$282 -> 0.0032579686 | E216: =D216*$E$3 -> 6710.6142 | F216: =E216/C216 -> 0.17013461 | H216: Grand Total | J216: 9496294.3 | K216: =J216/$J$216 -> 1 | L216: =K216*$E$4 -> 3673696.1 | M216: =L216/J216 -> 0.38685575 | O216: E01300 | P216: C385009 | Q216: 49907.98 | R216: =Q216/$Q$244 -> 0.0054734165 | S216: =R216*$E$5 -> 16102.899 | T216: =S216/Q216 -> 0.32265179
A217: E01300 | B217: C252125 | C217: 22290.2 | D217: =C217/$C$282 -> 0.0018411588 | E217: =D217*$E$3 -> 3792.3344 | F217: =E217/C217 -> 0.17013461 | O217: E01300 | P217: C503061 | Q217: 79982.02 | R217: =Q217/$Q$244 -> 0.0087716415 | S217: =R217*$E$5 -> 25806.342 | T217: =S217/Q217 -> 0.32265179
A218: E01300 | B218: C252129 | C218: 12642.24 | D218: =C218/$C$282 -> 0.0010442424 | E218: =D218*$E$3 -> 2150.8825 | F218: =E218/C218 -> 0.17013461 | O218: E01300 | P218: C505104 | Q218: 95201.45 | R218: =Q218/$Q$244 -> 0.010440759 | S218: =R218*$E$5 -> 30716.918 | T218: =S218/Q218 -> 0.32265179
A219: E01300 | B219: C252131 | C219: 58752.46 | D219: =C219/$C$282 -> 0.0048529223 | E219: =D219*$E$3 -> 9995.8267 | F219: =E219/C219 -> 0.17013461 | O219: E01300 | P219: C506034 | Q219: 18714.19 | R219: =Q219/$Q$244 -> 0.0020523883 | S219: =R219*$E$5 -> 6038.1669 | T219: =S219/Q219 -> 0.32265179
A220: E01300 | B220: C252133 | C220: 8857.54 | D220: =C220/$C$282 -> 0.00073162815 | E220: =D220*$E$3 -> 1506.9741 | F220: =E220/C220 -> 0.17013461 | O220: E01300 | P220: C380018 | Q220: 11101.81 | R220: =Q220/$Q$244 -> 0.0012175374 | S220: =R220*$E$5 -> 3582.0189 | T220: =S220/Q220 -> 0.32265179
A221: E01300 | B221: C253002 | C221: 88144.83 | D221: =C221/$C$282 -> 0.0072807167 | E221: =D221*$E$3 -> 14996.486 | F221: =E221/C221 -> 0.17013461 | O221: E01300 | P221: C505103 | Q221: 83243.19 | R221: =Q221/$Q$244 -> 0.0091292945 | S221: =R221*$E$5 -> 26858.564 | T221: =S221/Q221 -> 0.32265179
A222: E01300 | B222: C253005 | C222: 31684.85 | D222: =C222/$C$282 -> 0.002617152 | E222: =D222*$E$3 -> 5390.6895 | F222: =E222/C222 -> 0.17013461 | O222: E01300 | P222: C505105 | Q222: 112267.79 | R222: =Q222/$Q$244 -> 0.012312427 | S222: =R222*$E$5 -> 36223.403 | T222: =S222/Q222 -> 0.32265179
A223: E01300 | B223: C253011 | C223: 27653.93 | D223: =C223/$C$282 -> 0.0022842001 | E223: =D223*$E$3 -> 4704.8905 | F223: =E223/C223 -> 0.17013461 | O223: E01300 | P223: C400124 | Q223: 28153.86 | R223: =Q223/$Q$244 -> 0.0030876385 | S223: =R223*$E$5 -> 9083.8933 | T223: =S223/Q223 -> 0.32265179
A224: E01300 | B224: C253012 | C224: 166398.93 | D224: =C224/$C$282 -> 0.013744464 | E224: =D224*$E$3 -> 28310.217 | F224: =E224/C224 -> 0.17013461 | O224: E01300 | P224: C505100 | Q224: 44420.41 | R224: =Q224/$Q$244 -> 0.0048715938 | S224: =R224*$E$5 -> 14332.325 | T224: =S224/Q224 -> 0.32265179
A225: E01300 | B225: C253013 | C225: 54379.05 | D225: =C225/$C$282 -> 0.004491681 | E225: =D225*$E$3 -> 9251.7583 | F225: =E225/C225 -> 0.17013461 | O225: E01300 | P225: C500369 | Q225: 49408.72 | R225: =Q225/$Q$244 -> 0.0054186626 | S225: =R225*$E$5 -> 15941.812 | T225: =S225/Q225 -> 0.32265179
A226: E01300 | B226: C253014 | C226: 19426.67 | D226: =C226/$C$282 -> 0.0016046327 | E226: =D226*$E$3 -> 3305.1489 | F226: =E226/C226 -> 0.17013461 | O226: E01300 | P226: C506072 | Q226: 28767.12 | R226: =Q226/$Q$244 -> 0.0031548948 | S226: =R226*$E$5 -> 9281.7628 | T226: =S226/Q226 -> 0.32265179
A227: E01300 | B227: C253015 | C227: 10728.69 | D227: =C227/$C$282 -> 0.00088618416 | E227: =D227*$E$3 -> 1825.3215 | F227: =E227/C227 -> 0.17013461 | O227: E01300 | P227: C506073 | Q227: 17566.17 | R227: =Q227/$Q$244 -> 0.0019264848 | S227: =R227*$E$5 -> 5667.7562 | T227: =S227/Q227 -> 0.32265179
A228: E01300 | B228: C253019 | C228: 46078.3 | D228: =C228/$C$282 -> 0.0038060434 | E228: =D228*$E$3 -> 7839.5135 | F228: =E228/C228 -> 0.17013461 | O228: E01300 | P228: C500370 | Q228: 18059.57 | R228: =Q228/$Q$244 -> 0.0019805961 | S228: =R228*$E$5 -> 5826.9526 | T228: =S228/Q228 -> 0.32265179
... A243: E01300 | B243: C253710 | C243: 11514.89 | D243: =C243/$C$282 -> 0.00095112387 | E243: =D243*$E$3 -> 1959.0813 | F243: =E243/C243 -> 0.17013461 | O243: E01300 | P243: C515008 | Q243: 3269.23 | R243: =Q243/$Q$244 -> 0.000358537 | S243: =R243*$E$5 -> 1054.8229 | T243: =S243/Q243 -> 0.32265179
A244: E01300 | B244: C253711 | C244: 102379.41 | D244: =C244/$C$282 -> 0.0084564855 | E244: =D244*$E$3 -> 17418.281 | F244: =E244/C244 -> 0.17013461 | O244: Grand Total | Q244: 9118250 | R244: =Q244/$Q$244 -> 1 | S244: =R244*$E$5 -> 2942019.7 | T244: =S244/Q244 -> 0.32265179
A245: E01300 | B245: C253712 | C245: 82720.13 | D245: =C245/$C$282 -> 0.0068326393 | E245: =D245*$E$3 -> 14073.557 | F245: =E245/C245 -> 0.17013461
A246: E01300 | B246: C253714 | C246: 53163.87 | D246: =C246/$C$282 -> 0.0043913077 | E246: =D246*$E$3 -> 9045.0141 | F246: =E246/C246 -> 0.17013461
A247: E01300 | B247: C253716 | C247: 9550.69 | D247: =C247/$C$282 -> 0.00078888198 | E247: =D247*$E$3 -> 1624.9029 | F247: =E247/C247 -> 0.17013461
A248: E01300 | B248: C253722 | C248: 24218.97 | D248: =C248/$C$282 -> 0.0020004742 | E248: =D248*$E$3 -> 4120.4849 | F248: =E248/C248 -> 0.17013461
A249: E01300 | B249: C253723 | C249: 10742.62 | D249: =C249/$C$282 -> 0.00088733477 | E249: =D249*$E$3 -> 1827.6914 | F249: =E249/C249 -> 0.17013461
A250: E01300 | B250: C253727 | C250: 4916.35 | D250: =C250/$C$282 -> 0.00040608793 | E250: =D250*$E$3 -> 836.44128 | F250: =E250/C250 -> 0.17013461
A251: E01300 | B251: C254004 | C251: 244301.23 | D251: =C251/$C$282 -> 0.020179153 | E251: =D251*$E$3 -> 41564.094 | F251: =E251/C251 -> 0.17013461
A252: E01300 | B252: C254008 | C252: 7653.85 | D252: =C252/$C$282 -> 0.00063220399 | E252: =D252*$E$3 -> 1302.1848 | F252: =E252/C252 -> 0.17013461
A253: E01300 | B253: C254009 | C253: 2981.88 | D253: =C253/$C$282 -> 0.00024630172 | E253: =D253*$E$3 -> 507.32098 | F253: =E253/C253 -> 0.17013461
A254: E01300 | B254: C254018 | C254: 42072.9 | D254: =C254/$C$282 -> 0.0034751994 | E254: =D254*$E$3 -> 7158.0563 | F254: =E254/C254 -> 0.17013461
A255: E01300 | B255: C254021 | C255: 49297.06 | D255: =C255/$C$282 -> 0.0040719113 | E255: =D255*$E$3 -> 8387.1359 | F255: =E255/C255 -> 0.17013461
A256: E01300 | B256: C259000 | C256: 5000 | D256: =C256/$C$282 -> 0.00041299737 | E256: =D256*$E$3 -> 850.67303 | F256: =E256/C256 -> 0.17013461
... A281: E01300 | B281: C100940 | C281: 6219.69 | D281: =C281/$C$282 -> 0.00051374313 | E281: =D281*$E$3 -> 1058.1845 | F281: =E281/C281 -> 0.17013461
A282: Grand Total | C282: 12106614 | D282: =C282/$C$282 -> 1 | E282: =D282*$E$3 -> 2059754.1 | F282: =E282/C282 -> 0.17013461

Sheet Salary-FTE
A1: October 2025 Salaries per Cost Center | I1: Salary posted to the default CC C200591 is excluded from the allocation process
A3: Entity_Code | B3: Center_Code | C3: FTE | D3: Salary | E3: Segment
A4: E00330 | B4: C040414 | C4: 0 | D4: 1676 | E4: =VLOOKUP(B4,'CC by Segment'!$D:$E,2,FALSE) -> Corporate | G4: =TRIM(B4) -> C040414
A5: E00330 | B5: C301007 | C5: 0 | D5: 3576.92 | E5: =VLOOKUP(B5,'CC by Segment'!$D:$E,2,FALSE) -> Housing | G5: =TRIM(B5) -> C301007
A6: E00330 | B6: C301008 | C6: 0 | D6: 4769.23 | E6: =VLOOKUP(B6,'CC by Segment'!$D:$E,2,FALSE) -> Housing | G6: =TRIM(B6) -> C301008
A7: E00330 | B7: C350102 | C7: 0 | D7: 4876.65 | E7: =VLOOKUP(B7,'CC by Segment'!$D:$E,2,FALSE) -> Housing | G7: =TRIM(B7) -> C350102
A8: E00330 | B8: C350103 | C8: 0 | D8: 7224.19 | E8: =VLOOKUP(B8,'CC by Segment'!$D:$E,2,FALSE) -> Housing | G8: =TRIM(B8) -> C350103
A9: E00330 | B9: C350106 | C9: 0 | D9: 3556.88 | E9: =VLOOKUP(B9,'CC by Segment'!$D:$E,2,FALSE) -> Housing | G9: =TRIM(B9) -> C350106
A10: E00330 | B10: C350110 | C10: 0 | D10: 10415.43 | E10: =VLOOKUP(B10,'CC by Segment'!$D:$E,2,FALSE) -> Housing | G10: =TRIM(B10) -> C350110
A11: E00330 | B11: C350512 | C11: 0 | D11: 2178.72 | E11: =VLOOKUP(B11,'CC by Segment'!$D:$E,2,FALSE) -> Housing | G11: =TRIM(B11) -> C350512
A12: E00330 | B12: C350520 | C12: 0 | D12: 1920.9 | E12: =VLOOKUP(B12,'CC by Segment'!$D:$E,2,FALSE) -> Housing | G12: =TRIM(B12) -> C350520
A13: E00330 | B13: C350527 | C13: 0 | D13: 1838.16 | E13: =VLOOKUP(B13,'CC by Segment'!$D:$E,2,FALSE) -> Housing | G13: =TRIM(B13) -> C350527
A14: E00330 | B14: C350529 | C14: 0 | D14: 5145.18 | E14: =VLOOKUP(B14,'CC by Segment'!$D:$E,2,FALSE) -> Housing | G14: =TRIM(B14) -> C350529
A15: E00330 | B15: C350553 | C15: 0 | D15: 4440.77 | E15: =VLOOKUP(B15,'CC by Segment'!$D:$E,2,FALSE) -> Housing | G15: =TRIM(B15) -> C350553
... A157: E01300 | B157: C200561 | C157: 5 | D157: 22199.57 | E157: =VLOOKUP(B157,'CC by Segment'!$D:$E,2,FALSE) -> Corporate | G157: =TRIM(B157) -> C200561
A158: E01300 | B158: C200591 | C158: 0 | D158: 2470.14 | E158: 0 | G158: =TRIM(B158) -> C200591
A159: E01300 | B159: C200601 | C159: 3 | D159: 25784.66 | E159: =VLOOKUP(B159,'CC by Segment'!$D:$E,2,FALSE) -> Corporate | G159: =TRIM(B159) -> C200601
A160: E01300 | B160: C250000 | C160: 2 | D160: 23077.92 | E160: =VLOOKUP(B160,'CC by Segment'!$D:$E,2,FALSE) -> Corporate | G160: =TRIM(B160) -> C250000
A161: E01300 | B161: C250050 | C161: 12 | D161: 48754.67 | E161: =VLOOKUP(B161,'CC by Segment'!$D:$E,2,FALSE) -> Corporate | G161: =TRIM(B161) -> C250050
A162: E01300 | B162: C250051 | C162: 12 | D162: 53479.56 | E162: =VLOOKUP(B162,'CC by Segment'!$D:$E,2,FALSE) -> Corporate | G162: =TRIM(B162) -> C250051
A163: E01300 | B163: C250052 | C163: 5 | D163: 30261.19 | E163: =VLOOKUP(B163,'CC by Segment'!$D:$E,2,FALSE) -> Corporate | G163: =TRIM(B163) -> C250052
A164: E01300 | B164: C250100 | C164: 8 | D164: 39109.81 | E164: =VLOOKUP(B164,'CC by Segment'!$D:$E,2,FALSE) -> Corporate | G164: =TRIM(B164) -> C250100
A165: E01300 | B165: C250110 | C165: 5 | D165: 24707.72 | E165: =VLOOKUP(B165,'CC by Segment'!$D:$E,2,FALSE) -> Corporate | G165: =TRIM(B165) -> C250110
A166: E01300 | B166: C250112 | C166: 11 | D166: 45341.22 | E166: =VLOOKUP(B166,'CC by Segment'!$D:$E,2,FALSE) -> Corporate | G166: =TRIM(B166) -> C250112
A167: E01300 | B167: C250113 | C167: 1 | D167: 12580.04 | E167: =VLOOKUP(B167,'CC by Segment'!$D:$E,2,FALSE) -> Corporate | G167: =TRIM(B167) -> C250113
A168: E01300 | B168: C250120 | C168: 8 | D168: 31388.35 | E168: =VLOOKUP(B168,'CC by Segment'!$D:$E,2,FALSE) -> Corporate | G168: =TRIM(B168) -> C250120
A169: E01300 | B169: C250122 | C169: 18 | D169: 65709.81 | E169: =VLOOKUP(B169,'CC by Segment'!$D:$E,2,FALSE) -> Corporate | G169: =TRIM(B169) -> C250122
A170: E01300 | B170: C250123 | C170: 19 | D170: 94680.87 | E170: =VLOOKUP(B170,'CC by Segment'!$D:$E,2,FALSE) -> Corporate | G170: =TRIM(B170) -> C250123
... A710: E01300 | B710: C350726 | C710: 1 | D710: 5006.62 | E710: =VLOOKUP(B710,'CC by Segment'!$D:$E,2,FALSE) -> Housing | G710: =TRIM(B710) -> C350726
C711: =SUM(C4:C710) -> 10197 | D711: =SUM(D4:D710) -> 30723629

Sheet Email

Sheet FTE
A1: October 2025 FTE per Cost Center | H1: Salary posted to the default CC C200591 is excluded from the allocation process
A3: Entity_Code | B3: Center_Code | C3: FTE | E3: Rate | F3: ='Cash Calc.'!D6 -> 850.78649
A4: E00330 | B4: C040414 | C4: 0 | F4: =C4*$F$3 -> 0
A5: E00330 | B5: C301007 | C5: 0 | F5: =C5*$F$3 -> 0
A6: E00330 | B6: C301008 | C6: 0 | F6: =C6*$F$3 -> 0
A7: E00330 | B7: C350102 | C7: 0 | F7: =C7*$F$3 -> 0
A8: E00330 | B8: C350103 | C8: 0 | F8: =C8*$F$3 -> 0
A9: E00330 | B9: C350106 | C9: 0 | F9: =C9*$F$3 -> 0
A10: E00330 | B10: C350110 | C10: 0 | F10: =C10*$F$3 -> 0
A11: E00330 | B11: C350512 | C11: 0 | F11: =C11*$F$3 -> 0
A12: E00330 | B12: C350520 | C12: 0 | F12: =C12*$F$3 -> 0
A13: E00330 | B13: C350527 | C13: 0 | F13: =C13*$F$3 -> 0
A14: E00330 | B14: C350529 | C14: 0 | F14: =C14*$F$3 -> 0
A15: E00330 | B15: C350553 | C15: 0 | F15: =C15*$F$3 -> 0
... A710: E01300 | B710: C350726 | C710: 1 | F710: =C710*$F$3 -> 850.78649
C711: =SUM(C4:C710) -> 10197

Sheet GFS Cube
A2: Hier_Consol Sub Account Code Desc | B2: All
A3: Ledger Name | B3: (Multiple Items)
A4: GFSDM Last Updated | B4: All
A5: Dataset Last Refreshed | B5: All
B7: Column Labels
B8: 2025
B9: Oct-2025
A10: Row Labels | B10: Func Cur YTD | C10: USD Cur YTD
A11: E01300:American Bankers Insurance Company of Florida
A12: A700018-00:Group Ins - Emp Company Cost
A13: C200593:Group Insurance
A14: B000 | B14: 8675469.9 | C14: 8675469.9
A15: B100 | B15: 722467.74 | C15: 722467.74

Sheet Account
A1: GFS Sub account | B1: Account Description | C1: SS account | D1: Type Code (as a reference, not meant to be exhaustive list) | E1: Date of Changes | I1: SS Account GFS | J1: GFS Account (check) | K1: In EDM Yes/No
A2: A105098-00 | B2: Inv Def Comp - Executive 401k Plan | C2: 12060000 | D2: MIPSP | J2: A105098-00 | K2: Yes
A3: A105099-00 | B3: Invested Deferred Compensation Asset | C3: 12062000 | J3: A105099-00 | K3: Yes
A4: A105099-01 | B4: Inv Def Comp - Frozen Plans | C4: 12062000 | D4: FOR | J4: A105099-01 | K4: Yes
A5: A105099-02 | B5: Inv Def Comp - Active Plans | C5: 12062000 | D5: ADC | J5: A105099-02 | K5: Yes
A6: A105100-00 | B6: Policy Loans - Dir | C6: 10500000 | D6: Policy Loans | J6: A105100-00 | K6: Yes
A7: A105111-00 | B7: Loans Loss Reserve | C7: 10480001 | J7: A105111-00 | K7: Yes
A8: A105200-00 | B8: Policy Loans - Asmd NonAffil | C8: 10500100 | J8: A105200-00 | K8: Yes
A9: A105300-00 | B9: Policy Loans - Ced NonAffil | C9: 10500200 | J9: A105300-00 | K9: Yes
A10: A105900-00 | B10: Policy Loans - NonAdmit | C10: 10500600 | J10: A105900-00 | K10: Yes
A11: A1T0017-00 | B11: ST Inv Other Non Aflt | C11: 10099000 | J11: A1T0017-00 | K11: Yes
A12: A1T0108-00 | B12: Csh In Office | C12: 10800000 | J12: A1T0108-00 | K12: Yes
A13: A1T0126-00 | B13: Cash Other | C13: 10899000 | J13: A1T0126-00 | K13: Yes
A14: A115000-00 | B14: Due To (From) Parent and Affiliates | C14: 14300000 | D14: (add appropriate affil) | J14: A115000-00 | K14: Yes
A15: A115000-00 | B15: Due To (From) Parent and Affiliates | C15: 14208101 | D15: E00901 | J15: A115000-00 | K15: Yes
A16: A115000-00 | B16: Due To (From) Parent and Affiliates | C16: 14208186 | D16: E00730 | J16: A115000-00 | K16: Yes
A17: A115000-00 | B17: Due To (From) Parent and Affiliates | C17: 14208530 | D17: E00721 | J17: A115000-00 | K17: Yes
A18: A115000-00 | B18: Due To (From) Parent and Affiliates | C18: 14208532 | D18: E00711 | J18: A115000-00 | K18: Yes
A19: A115000-00 | B19: Due To (From) Parent and Affiliates | C19: 14208534 | D19: E00711 | J19: A115000-00 | K19: Yes
A20: A115000-00 | B20: Due To (From) Parent and Affiliates | C20: 14208640 | D20: E00912 | J20: A115000-00 | K20: Yes
A21: A115000-00 | B21: Due To (From) Parent and Affiliates | C21: 14301000 | D21: E00001 | J21: A115000-00 | K21: Yes
A22: A115000-00 | B22: Due To (From) Parent and Affiliates | C22: 14308001 | D22: E00330 | J22: A115000-00 | K22: Yes
A23: A115000-00 | B23: Due To (From) Parent and Affiliates | C23: 14308005 | D23: E00302 | J23: A115000-00 | K23: Yes
A24: A115000-00 | B24: Due To (From) Parent and Affiliates | C24: 14308008 | D24: E00301 | J24: A115000-00 | K24: Yes
A25: A115000-00 | B25: Due To (From) Parent and Affiliates | C25: 14308101 | D25: E00901 | J25: A115000-00 | K25: Yes
... A145: A115000-00 | B145: Due To (From) Parent and Affiliates | C145: 14308989 | D145: E01200 | J145: A115000-00 | K145: Yes
A146: A115000-00 | B146: Due To (From) Parent and Affiliates | C146: 14208V09 | D146: E00530 | J146: A115000-00 | K146: Yes
A147: A115000-00 | B147: Due To (From) Parent and Affiliates | C147: 14208V17 | D147: E00531 | J147: A115000-00 | K147: Yes
A148: A115000-00 | B148: Due To (From) Parent and Affiliates | C148: 14308IA2 | D148: E00804 | J148: A115000-00 | K148: Yes
A149: A115000-00 | B149: Due To (From) Parent and Affiliates | C149: 14308IA3 | D149: E00805 | J149: A115000-00 | K149: Yes
A150: A115000-00 | B150: Due To (From) Parent and Affiliates | C150: 14308IAT | D150: E00631 | J150: A115000-00 | K150: Yes
A151: A115000-00 | B151: Due To (From) Parent and Affiliates | C151: 14308IAU | D151: E00632 | J151: A115000-00 | K151: Yes
A152: A115000-00 | B152: Due To (From) Parent and Affiliates | C152: 14308IAV | D152: E00635 | J152: A115000-00 | K152: Yes
A153: A115000-00 | B153: Due To (From) Parent and Affiliates | C153: 14308IBC | D153: E00809 | J153: A115000-00 | K153: Yes
A154: A115000-00 | B154: Due To (From) Parent and Affiliates | C154: 14308IBS | D154: E00909 | J154: A115000-00 | K154: Yes
A155: A115000-00 | B155: Due To (From) Parent and Affiliates | C155: 14308IBZ | D155: E00821 | J155: A115000-00 | K155: Yes
A156: A115000-00 | B156: Due To (From) Parent and Affiliates | C156: 14308ICD | D156: E00806 | J156: A115000-00 | K156: Yes
A157: A115000-00 | B157: Due To (From) Parent and Affiliates | C157: 14308ICL | D157: E00808 | J157: A115000-00 | K157: Yes
... A197: A115000-00 | B197: Due To (From) Parent and Affiliates | C197: 14308V17 | D197: E00531 | J197: A115000-00 | K197: Yes
A198: A115000-00 | B198: Due To (From) Parent and Affiliates | C198: 14301020 | D198: E00300 | J198: A115000-00 | K198: Yes
A199: A115000-00 | B199: Due To (From) Parent and Affiliates | C199: 14301004 | D199: E00300 | J199: A115000-00 | K199: Yes
A200: A115000-00 | B200: Due To (From) Parent and Affiliates | C200: 14308INI | D200: E00637 | J200: A115000-00 | K200: Yes
A201: A115000-00 | B201: Due To (From) Parent and Affiliates | C201: 14301010 | D201: E00300 | J201: A115000-00 | K201: Yes
A202: A115000-00 | B202: Due To (From) Parent and Affiliates | C202: 14305000 | D202: E00004 | J202: A115000-00 | K202: Yes
A203: A115000-00 | B203: Due To (From) Parent and Affiliates | C203: 14308002 | D203: E00331 | J203: A115000-00 | K203: Yes
A204: A115000-00 | B204: Due To (From) Parent and Affiliates | C204: 14308526 | D204: E00100 | J204: A115000-00 | K204: Yes
A205: A115000-00 | B205: Due To (From) Parent and Affiliates | C205: 14308548 | D205: E00111 | J205: A115000-00 | K205: Yes
A206: A115000-00 | B206: Due To (From) Parent and Affiliates | C206: 14308N31 | D206: E00101 | J206: A115000-00 | K206: Yes
A207: A115000-00 | B207: Due To (From) Parent and Affiliates | C207: 14308S03 | D207: E00950 | J207: A115000-00 | K207: Yes
A208: A115000-00 | B208: Due To (From) Parent and Affiliates | C208: 14317250 | D208: E01503 | J208: A115000-00 | K208: Yes
A209: A115000-00 | B209: Due To (From) Parent and Affiliates | C209: 14317251 | D209: E01504 | J209: A115000-00 | K209: Yes
A210: A115000-00 | B210: Due To (From) Parent and Affiliates | C210: 14317252 | D210: E00352 | J210: A115000-00 | K210: Yes
A211: A115010-00 | B211: Intercompany Receivable - Nonadmit | C211: 14300600 | J211: A115010-00 | K211: Yes
A212: A255000-00 | B212: Intercompany Payable | D212: (for STAT purposes) | J212: A255000-00 | K212: Yes
A213: A110100-00 | B213: Premiums Due - Dir | C213: 12400000 | J213: A110100-00 | K213: Yes
A214: A110100-01 | B214: Premiums Due - FY - Dir | C214: 12400000 | J214: A110100-01 | K214: Yes
A215: A110100-11 | B215: Premiums Due - Renewal - Dir | C215: 12404000 | J215: A110100-11 | K215: Yes
A216: A110102-00 | B216: Premiums Deferred - Dir | J216: A110102-00 | K216: Yes
A217: A110102-01 | B217: Premiums Deferred - FY - Dir | C217: 12800000 | J217: A110102-01 | K217: Yes
A218: A110102-11 | B218: Premiums Deferred - Renewal - Dir | C218: 12804000 | J218: A110102-11 | K218: Yes
A219: A110120-00 | B219: AH Premiums Due and Unpaid - Dir | C219: 19852000 | J219: A110120-00 | K219: Yes
A220: A110200-00 | B220: Premiums Due - Asmd NonAffil | C220: 12400100 | J220: A110200-00 | K220: Yes
A221: A110200-01 | B221: Premiums Due - FY - Asmd NonAffil | C221: 12400100 | J221: A110200-01 | K221: Yes
A222: A110202-00 | B222: Premiums Deferred - Asmd NonAffil | C222: 12800100 | J222: A110202-00 | K222: Yes
A223: A110202-01 | B223: Premiums Deferred - FY - Asmd NonAffil | C223: 12800100 | J223: A110202-01 | K223: Yes
A224: A110202-11 | B224: Premiums Deferred - Renewal - Asmd NonAffil | C224: 12804100 | J224: A110202-11 | K224: Yes
A225: A110300-00 | B225: Premiums Due - Ced NonAffil | C225: 12400200 | J225: A110300-00 | K225: Yes
A226: A110300-01 | B226: Premiums Due - FY - Ced NonAffil | C226: 12400200 | J226: A110300-01 | K226: Yes
A227: A110300-11 | B227: Premiums Due - Renewal - Ced NonAffil | C227: 12404200 | J227: A110300-11 | K227: Yes
A228: A110700-00 | B228: Insurance Receivables - Cash Clearing | C228: 12400000 | J228: A110700-00 | K228: Yes
... A231: A110900-00 | B231: Insurance Receivables - Nonadmit | C231: 12404600 | J231: A110900-00 | K231: Yes
A232: A110900-00 | B232: Insurance Receivables - Nonadmit | C232: 12400600 | D232: Type codes in sys: DMO | E232: FAS | F232: PMS | G232: Exceed | H232: CAS | J232: A110900-00 | K232: Yes
A233: A111000-00 | B233: Agents Balances | C233: 16000000 | D233: RDM00 | E233: RXY00 | F233: RPM00 | H233: RWA00 | J233: A111000-00 | K233: Yes
A234: A111000-01 | B234: Agents Bal - Cash Receipts Suspense | C234: 16000000 | D234: RDM01 | E234: RXY01 | F234: RPM01 | H234: RWA01 | J234: A111000-01 | K234: Yes
A235: A111000-02 | B235: Agents Bal - Premium Clearing | C235: 16000000 | D235: RDM02 | E235: RXY02 | F235: RPM02 | H235: RWA02 | J235: A111000-02 | K235: Yes
A236: A111000-03 | B236: Agents Bal - Cash Disb Suspense | C236: 16000000 | D236: RPRDW03 | F236: RPM03 | J236: A111000-03 | K236: Yes
A237: A111000-04 | B237: Agents Bal - Commissions | C237: 16012000 | J237: A111000-04 | K237: Yes
A238: A111000-05 | B238: Agents Bal - Accrued | C238: 16000000 | D238: 1282001 | J238: A111000-05 | K238: Yes
A239: A111010-00 | B239: Dealer Balances Receivable TPA | C239: 16000000 | J239: A111010-00 | K239: Yes
A240: A111010-01 | B240: Dealer Balances Receivable TPA - Unapplied Cash | C240: 16000000 | J240: A111010-01 | K240: Yes
A241: A111010-04 | B241: Dealer Balances Receivable - Lag Accural | C241: 16000000 | J241: A111010-04 | K241: Yes
A242: A111020-00 | B242: Dealer Balances Receivable Admin | C242: 16000000 | J242: A111020-00 | K242: Yes
A243: A111020-01 | B243: Dealer Balances Receivable Admin - Unapplied Cash | C243: 16000000 | J243: A111020-01 | K243: Yes
A244: A111101-00 | B244: Agents Balances - Consumer Direct Retail | C244: 16008000 | D244: RDB01 | J244: A111101-00 | K244: Yes
A245: A111101-00 | B245: Agents Balances - Consumer Direct Retail | C245: 16000000 | D245: RWCUST | J245: A111101-00 | K245: Yes
A246: A111101-01 | B246: Agents Bal - CD - Cash Receipts (Suspense) | C246: 16008000 | J246: A111101-01 | K246: Yes
A247: A111101-02 | B247: Agents Bal - CD - Prem Clearing | C247: 16008000 | D247: RPM00,RPM03 | J247: A111101-02 | K247: Yes
A248: A111101-03 | B248: Agents Bal - CD - Cash Disb Suspense | C248: 16008000 | J248: A111101-03 | K248: Yes
A249: A111102-00 | B249: Commissions PIA - Dir | C249: 16014000 | J249: A111102-00 | K249: Yes
A250: A111109-00 | B250: Installment Prem Bkd Ndue | C250: 16008000 | D250: RBSM00 | G250: RBAM00 | J250: A111109-00 | K250: Yes
A251: A111109-01 | B251: Installment Prem Bkd Ndue - Cash Rec Suspense | C251: 16008000 | D251: RBSM01 | G251: RBAM01 | J251: A111109-01 | K251: Yes
A252: A111109-02 | B252: Installment Prem Bkd Ndue - Prem Clearing | C252: 16008000 | D252: RBSM02 | G252: RBAM02 | J252: A111109-02 | K252: Yes
A253: A111109-03 | B253: Installment Prem Bkd Ndue - Cash Disb Suspense | C253: 16008000 | D253: RBSM03 | G253: RBAM03 | J253: A111109-03 | K253: Yes
A254: A111109-04 | B254: Installment Prem Bkd Ndue - Unidentified Cash | C254: 16008000 | D254: RBSM21 | G254: RBAM21 | J254: A111109-04 | K254: Yes
A255: A111109-05 | B255: Installment Prem Bkd Ndue - Cash on Hold Suspense | C255: 16008000 | D255: RBSM11 | G255: RBAM11 | J255: A111109-05 | K255: Yes
A256: A111109-06 | B256: Installment Comm Bkd Ndue - Cash Rec Clearing | C256: 16008000 | D256: RBS01 | J256: A111109-06 | K256: Yes
A257: A111109-07 | B257: Installment Comm Bkd Ndue - Disbursements | C257: 16008000 | D257: RBS03, RBA03 | J257: A111109-07 | K257: Yes
A258: A111109-08 | B258: Installment Comm Bkd Ndue - ACH & CC | C258: 16008000 | D258: RBSM31 and RSD31 | J258: A111109-08 | K258: Yes
A259: A111109-09 | B259: Installment Prem Bkd Ndue - Cash Receipt Clearing | C259: 16008000 | D259: RDB01 | J259: A111109-09 | K259: Yes
A260: A111200-00 | B260: Agents Balances - Asmd NonAffil | C260: 16000100 | J260: A111200-00 | K260: Yes
...

Sheet Cost Center
A1: SS Cost Center | B1: SS Cost Center Description | C1: GFS Center | D1: GFS Center Description | F1: Location Code | G1: Descriptions | H1: In EDM Yes/No
A2: 113040 | B2: 113040-Office Of CFO | C2: C010000 | D2: Finance - Chief Financial Officer | F2: L0001 | G2: U.S. Home Office | H2: Yes | I2: 113040
A3: 2005 | B3: 2005-Reinsurance Marketing | C3: C400030 | D3: Global Auto - Reinsurance Marketing | F3: L0001 | G3: U.S. Home Office | H3: Yes | I3: 2005
A4: 11112 | B4: 11112-CLAIMS ACCOUNTING DFS | C4: C010101 | D4: Global Accouting - CAO | F4: L0001 | G4: U.S. Home Office | H4: Yes | I4: 11112
A5: 2015 | B5: 2015-CarMax & Digital Auto | C5: C400025 | D5: Global Auto - CarMax & Digital Auto | H5: Yes | I5: 2015
A6: 2035 | B6: 2035-Pacific NW | C6: C400115 | D6: Global Auto - ADS - Pacific NW | H6: Yes | I6: 2035
A7: 1013402 | B7: 1013402-Investment Accounting | C7: C010105 | D7: Global Accounting - Investments | F7: L0001 | G7: U.S. Home Office | H7: Yes | I7: 1013402
A8: 113230 | B8: 113230-Financial And Sec Reporting | C8: C010110 | D8: Global Accounting - Financial and SEC Reporting | F8: L0001 | G8: U.S. Home Office | H8: Yes | I8: 113230
A9: 2075 | B9: 2075-Workforce Management | C9: C380008 | D9: VPS Ops - Workforce Management | H9: Yes | I9: 2075
A10: 3015 | B10: 3015-Service Admin-Chicago | C10: C515305 | D10: CL - HRO - TWG - Service Admin-Chicago | F10: L0001 | G10: U.S. Home Office | H10: Yes | I10: 3015
A11: 113049 | B11: 113049-Accounting & Finance Services | C11: C010121 | D11: Global Accounting - AFS Admin | F11: L0001 | G11: U.S. Home Office | H11: Yes | I11: 113049
A12: 5002 | B12: 5002:NETWORK AND SYSTEMS | C12: C254015 | D12: GT - TWG Apps - Network and Systems | H12: Yes | I12: 5002
A13: 5003 | B13: 5003:SECURITY PHOENIX | C13: C254019 | D13: GT - TWG Apps - Security Phoenix | H13: Yes | I13: 5003
A14: 5007 | B14: 5007-Help Desk & Desktop Spprt | C14: C254009 | D14: GT - TWG Apps - Help Desk and Desktop Support | F14: L0001 | G14: U.S. Home Office | H14: Yes | I14: 5007
A15: 5012 | B15: 5012:GLOW PROGRAM SOFTWARE | C15: C254007 | D15: GT - TWG Apps - GLOW Program Software | H15: Yes | I15: 5012
A16: 5013 | B16: 5013-IT Executive | C16: C254013 | D16: GT - TWG Apps - IT Executive | F16: L0001 | G16: U.S. Home Office | H16: Yes | I16: 5013
A17: 5014 | B17: 5014:GLOW & AIM LIFESTYLE PROJECT | C17: C254023 | D17: GT - TWG Apps - GLOW AIM Lifestyle Project | H17: Yes | I17: 5014
A18: 5015 | B18: 5015:TWG PUBLIC CLOUD | C18: C254017 | D18: GT - TWG Apps - Public Cloud | H18: Yes | I18: 5015
A19: 5016 | B19: 5016:LEGACY SYSTEM SUPPORT | C19: C254014 | D19: GT - TWG Apps - Legacy System Support | H19: Yes | I19: 5016
A20: 5017 | B20: 5017- UDB & AIM | C20: C254021 | D20: GT - TWG Apps - UDB & AIM | F20: L0001 | G20: U.S. Home Office | H20: Yes | I20: 5017
A21: 10200 | B21: 10200-LFS Segment Financial Reporting | C21: C010160 | D21: Global Accounting - Lifestyle Financial Reporting | F21: L0001 | G21: U.S. Home Office | H21: Yes | I21: 10200
A22: 10202 | B22: 10202-FIN REP MIA CROSS SELL ELIMINATIONS | C22: C010160 | D22: Global Accounting - Lifestyle Financial Reporting | F22: L0001 | G22: U.S. Home Office | H22: Yes | I22: 10202
A23: 6019 | B23: 6019-External Reporting | C23: C010160 | D23: Global Accounting - Lifestyle Financial Reporting | F23: L0001 | G23: U.S. Home Office | H23: Yes | I23: 6019
A24: 10271 | B24: 10271-CL Operations | C24: C010161 | D24: Global Accounting - Connected Living Acctg Ops | F24: L0001 | G24: U.S. Home Office | H24: Yes | I24: 10271
A25: 10228 | B25: 10228-GENERAL ACCOUNTING S&R | C25: C010162 | D25: Global Accounting - Mobile Accounting | F25: L0001 | G25: U.S. Home Office | H25: Yes | I25: 10228
A26: 5019 | B26: 5019- Cloud Technologies | C26: C254004 | D26: GT - TWG Apps - Cloud Technologies | F26: L0001 | G26: U.S. Home Office | H26: Yes | I26: 5019
A27: 10272 | B27: 10272-Mobile Accounting | C27: C010162 | D27: Global Accounting - Mobile Accounting | F27: L0001 | G27: U.S. Home Office | H27: Yes | I27: 10272
A28: WS712 | B28: WS712-GEN ACCTG CWORK | C28: C010162 | D28: Global Accounting - Mobile Accounting | F28: L0001 | G28: U.S. Home Office | H28: Yes | I28: WS712
A29: 10273 | B29: 10273-HRO and FS Accounting | C29: C010163 | D29: Global Accounting - HRO and FS Accounting | F29: L0001 | G29: U.S. Home Office | H29: Yes | I29: 10273
A30: W20100 | B30: W20100-ESC Financial Reporting | C30: C010163 | D30: Global Accounting - HRO and FS Accounting | F30: L0001 | G30: U.S. Home Office | H30: Yes | I30: W20100
A31: 5020 | B31: 5020:TWG INFRASTRUCTURE | C31: C254011 | D31: GT - TWG Apps - Infrastructure | H31: Yes | I31: 5020
A32: 5021 | B32: 5021-Reporting | C32: C254018 | D32: GT - TWG Apps - Reporting | F32: L0001 | G32: U.S. Home Office | H32: Yes | I32: 5021
A33: 10274 | B33: 10274-Auto Accounting | C33: C010164 | D33: Global Accounting - Auto Accounting | F33: L0001 | G33: U.S. Home Office | H33: Yes | I33: 10274
A34: AA006 | B34: AA006-AFAS ACCOUNTING | C34: C010164 | D34: Global Accounting - Auto Accounting | F34: L0001 | G34: U.S. Home Office | H34: Yes | I34: AA006
A35: U9922 | B35: U9922-VPS ACCOUNTING | C35: C010164 | D35: Global Accounting - Auto Accounting | F35: L0001 | G35: U.S. Home Office | H35: Yes | I35: U9922
A36: WS400 | B36: WS400-Financial Operations | C36: C010165 | D36: Global Accounting - Mobile Financial Ops | F36: L0001 | G36: U.S. Home Office | H36: Yes | I36: WS400
A37: 10223 | B37: 10223-GLOW AND AIM PROJECT | C37: C010166 | D37: Global Accounting - GLOW and AIM Project | F37: L0001 | G37: U.S. Home Office | H37: Yes | I37: 10223
A38: 5022 | B38: 5022:WARRANTY LINK | C38: C254022 | D38: GT - TWG Apps - Warranty Link | H38: Yes | I38: 5022
A39: 5024 | B39: 5024:APAC LAM MANAGEMENT | C39: C254001 | D39: GT - TWG Apps - APAC LAM Mgt | H39: Yes | I39: 5024
A40: 5026 | B40: 5026:INTERNATIONAL PROJECTS | C40: C254012 | D40: GT - TWG Apps - International Projects | H40: Yes | I40: 5026
A41: 10232 | B41: 10232-Actuarial Connected Living | C41: C010210 | D41: Actuarial - Connected Living | F41: L0001 | G41: U.S. Home Office | H41: Yes | I41: 10232
A42: U9913 | B42: U9913-Actuarial Global Auto | C42: C010215 | D42: Actuarial - Global Auto | F42: L0001 | G42: U.S. Home Office | H42: Yes | I42: U9913
A43: 10264 | B43: 10264-Actuarial Global Housing | C43: C010220 | D43: Actuarial - Global Housing | F43: L0001 | G43: U.S. Home Office | H43: Yes | I43: 10264
A44: 5027 | B44: 5027:TWG TELECOM | C44: C254020 | D44: GT - TWG Apps - Telecom | H44: Yes | I44: 5027
A45: 10230RC | B45: 10230RC-INTERNATIONAL ACTUARIAL | C45: C010235 | D45: Actuarial - International | H45: Yes | I45: 10230RC
A46: 5029 | B46: 5029:GLOW SUPPORT | C46: C254008 | D46: GT - TWG Apps - GLOW Support | F46: L0001 | G46: U.S. Home Office | H46: Yes | I46: 5029
A47: 5030 | B47: 5030-TWG Executive | C47: C700042 | D47: Mgt Fee - TWG Executive | H47: Yes | I47: 5030
A48: 5031 | B48: 5031-Asia Pacific Exec | C48: C390017 | D48: Lifestyle -Asia Pacific Executive | H48: Yes | I48: 5031
A49: 113233 | B49: 113233-Enterprise FP And A | C49: C010401 | D49: FPA - Enterprise 113233 | F49: L0001 | G49: U.S. Home Office | H49: Yes | I49: 113233
A50: 113100 | B50: 113100-Corporate FP and A | C50: C010410 | D50: FPA - Corporate | F50: L0001 | G50: U.S. Home Office | H50: Yes | I50: 113100
A51: 113232 | B51: 113232-IT Finance Executive | C51: C010415 | D51: FPA - IT Finance | F51: L0001 | G51: U.S. Home Office | H51: Yes | I51: 113232
A52: 5032 | B52: 5032-Exec | C52: C515000 | D52: CL - HRO - Executive | F52: L0001 | G52: U.S. Home Office | H52: Yes | I52: 5032
A53: 13100 | B53: 13100-Client Analysis ATL | C53: C010430 | D53: FPA - Housing | F53: L0001 | G53: U.S. Home Office | H53: Yes | I53: 13100
A54: 39701 | B54: 39701-CFO ASP | C54: C010431 | D54: FPA - Housing - CFO ASP | F54: L0001 | G54: U.S. Home Office | H54: Yes | I54: 39701
A55: 39702 | B55: 39702-Finance Ls Ops | C55: C010432 | D55: FPA - Housing - Finance LS Ops | F55: L0001 | G55: U.S. Home Office | H55: Yes | I55: 39702
A56: 46201 | B56: 46201-Lending Solutions Finance | C56: C010433 | D56: FPA - Housing - Lending Solutions Finance | F56: L0001 | G56: U.S. Home Office | H56: Yes | I56: 46201
A57: 5033 | B57: 5033-Financial Services | C57: C515007 | D57: CL - HRO - Financial Services | F57: L0001 | G57: U.S. Home Office | H57: Yes | I57: 5033
A58: 5039 | B58: 5039-Auto Claims | C58: C385005 | D58: VPS Ops - Auto Claims | F58: L0001 | G58: U.S. Home Office | H58: Yes | I58: 5039
A59: U9933 | B59: U9933-EPS Finance | C59: C010451 | D59: FPA - Auto | F59: L0001 | G59: U.S. Home Office | H59: Yes | I59: U9933
A60: 5040 | B60: 5040-Ops Mgmt | C60: C380009 | D60: VPS Ops - Ops Management | H60: Yes | I60: 5040
A61: WS702 | B61: WS702-Finance CWork | C61: C010453 | D61: FPA - Mobile Cwork | F61: L0121 | G61: York Office - Willow Springs | H61: Yes | I61: WS702
A62: 113220 | B62: 113220-Corporate Tax | C62: C010501 | D62: Tax - Corporate | F62: L0001 | G62: U.S. Home Office | H62: Yes | I62: 113220
A63: 6010 | B63: 6010-Taxes & Assessments | C63: C010595 | D63: Taxes and Assessments | H63: Yes | I63: 6010
A64: 5041 | B64: 5041-Payment Processing | C64: C380007 | D64: VPS Ops - Payment Processing | F64: L0001 | G64: U.S. Home Office | H64: Yes | I64: 5041
A65: 5042 | B65: 5042-CLAIMS AIZ INDIA | C65: C380010 | D65: VPS Ops - Claims AIZ India | H65: Yes | I65: 5042
A66: 113224 | B66: 113224-OTHER TAXES LICENSES AND FEES | C66: C010598 | D66: Other Taxes Licenses and Fees | H66: Yes | I66: 113224
A67: 6100 | B67: 6100-Treasury, AP & AR | C67: C010698 | D67: Treasury AP and AR | H67: Yes | I67: 6100
A68: 17000 | B68: 17000-BANK FEES TREASURY MANAGEMENT | C68: C010699 | D68: Treasury - Bank Fees | H68: Yes | I68: 17000
A69: 5043 | B69: 5043-PAYMENTS AIZ INDIA | C69: C380011 | D69: VPS Ops - Payments AIZ India | H69: Yes | I69: 5043
A70: 5044 | B70: 5044-TESTING AIZ INDIA | C70: C380012 | D70: VPS Ops - Testing AIZ India | H70: Yes | I70: 5044
A71: 5045 | B71: 5045-OPERATIONAL DCM INITIATIVES | C71: C380013 | D71: VPS Ops - Operational DCM initiatives | H71: Yes | I71: 5045
A72: 8000040 | B72: 8000040-INVESTMENT EXPENSES | C72: C010799 | D72: Investment Expenses | H72: Yes | I72: 8000040
A73: 113240 | B73: 113240:TREASURY | C73: C010800 | D73: Treasury | H73: Yes | I73: 113240
A74: 113020 | B74: 113020-Capital And Financial Ratings | C74: C010801 | D74: Capital and Financial Ratings | F74: L0001 | G74: U.S. Home Office | H74: Yes | I74: 113020
A75: 122000 | B75: 122000:Global Risk Modeling and Insurance Purchasing | C75: C010805 | D75: Global Risk Modeling and Insurance Purchasing | H75: Yes | I75: 122000
A76: 5046 | B76: 5046:FINANCIAL SYSTEMS IT | C76: C254006 | D76: GT - TWG Apps - Financial Systems IT | H76: Yes | I76: 5046
A77: 5047 | B77: 5047:HR SYSTEMS IT | C77: C254010 | D77: GT - TWG Apps - HR Systems | H77: Yes | I77: 5047
A78: 113002 | B78: 113002-NETWORK OPERATIONS | C78: C010902 | D78: Network Operations | H78: Yes | I78: 113002
A79: 5048 | B79: 5048:Corp Systems & IT Risk | C79: C254005 | D79: GT - TWG Apps - Corp Sys and IT Risk | H79: Yes | I79: 5048
A80: 113060 | B80: 113060-Office Of Chief Legal Officer | C80: C020201 | D80: Legal - Office of the Chief Legal Officer | F80: L0001 | G80: U.S. Home Office | H80: Yes | I80: 113060
A81: 5049 | B81: 5049-INCONTACT | C81: C380014 | D81: VPS Ops - Incontact | H81: Yes | I81: 5049
A82: 5050 | B82: 5050-DATA MGT AIZ INDIA | C82: C380015 | D82: VPS Ops - Data Management AIZ India | H82: Yes | I82: 5050
A83: 5056 | B83: 5056-Auto TPA | C83: C400031 | D83: Global Auto - Auto TPA | H83: Yes | I83: 5056
A84: 7487 | B84: 7487-Legal APAC Other | C84: C020206 | D84: Legal - Other | H84: Yes | I84: 7487
A85: 5058 | B85: 5058-ESC | C85: C515307 | D85: CL - HRO - ESC | H85: Yes | I85: 5058
A86: 5061 | B86: 5061-Latin America Exec | C86: C390018 | D86: Lifestyle -Latin America Executive | H86: Yes | I86: 5061
A87: 113290 | B87: 113290-Compliance Enterprise Expenses | C87: C020402 | D87: Legal - Compliance - Corporate | F87: L0001 | G87: U.S. Home Office | H87: Yes | I87: 113290
A88: 93031 | B88: 93031-Business Unit Compliance Mgmt | C88: C020405 | D88: Legal - Compliance - Business Unit Compliance Mgt | F88: L0001 | G88: U.S. Home Office | H88: Yes | I88: 93031
A89: 5062 | B89: 5062-CUSTOMER OPERATIONS VENDOR | C89: C380016 | D89: VPS Ops - Customer Operations Vendor | H89: Yes | I89: 5062
A90: 93032 | B90: 93032-Compliance Testing & Monitoring | C90: C020420 | D90: Legal - Compliance - Testing and Monitoring | F90: L0001 | G90: U.S. Home Office | H90: Yes | I90: 93032
A91: 10018AU | B91: 10018AU-ALEGRE LEGAL & COMPLIANCE | C91: C020421 | D91: Legal - Legal and Compliance - Alegre | H91: Yes | I91: 10018AU
A92: 113291 | B92: 113291-Ethics | C92: C020425 | D92: Legal - Ethics | F92: L0001 | G92: U.S. Home Office | H92: Yes | I92: 113291
A93: 113030 | B93: 113030-Government Relations | C93: C020501 | D93: Legal - Government Relations | F93: L0001 | G93: U.S. Home Office | H93: Yes | I93: 113030
A94: 21101 | B94: 21101-Litigation And HR Practice Group ATL | C94: C020502 | D94: Legal - Litigation and HR Practice Group | F94: L0001 | G94: U.S. Home Office | H94: Yes | I94: 21101
A95: 5064 | B95: 5064-RDG Mexico | C95: C390019 | D95: Lifestyle -RDG Mexico | H95: Yes | I95: 5064
A96: 10070 | B96: 10070-Privacy Operations | C96: C020601 | D96: Legal - Privary Operations | F96: L0001 | G96: U.S. Home Office | H96: Yes | I96: 10070
A97: 6005 | B97: 6005-Regulatory Affairs | C97: C390024 | D97: Lifestyle -Regulatory Affairs | H97: Yes | I97: 6005
A98: 10370FR | B98: 10370FR-DATA PRIVACY FR | C98: C020603 | D98: Legal - Data Privacy Internationa; | H98: Yes | I98: 10370FR
A99: 6015 | B99: 6015-US HR | C99: C390030 | D99: Lifestyle - US HR | H99: Yes | I99: 6015
A100: 93709 | B100: 93709-LITIGATION EXPENSE INTERNATIONAL | C100: C020902 | D100: Legal and Litigation Costs - International | H100: Yes | I100: 93709
...

Sheet CC by Segment
A1: Cost Center Number | B1: Cost Center Details | C1: GFS CC | D1: Vlookup | E1: Segment
A2: 1013600 | B2: 1013600:SYRACUSE, NY FACILITY | C2: =VLOOKUP(A2,'Cost Center'!A:C,3,FALSE) -> #N/A | D2: C900000 | E2: Corporate | F2: 1013600
A3: 113048 | B3: 113048:CORPORATE MOBILITY | C3: =VLOOKUP(A3,'Cost Center'!A:C,3,FALSE) -> C200225 | D3: C200225 | E3: Corporate | F3: 113048
A4: 114005 | B4: 114005:PBP ENTERPRISE COO | C4: =VLOOKUP(A4,'Cost Center'!A:C,3,FALSE) -> C200509 | D4: C200509 | E4: Corporate | F4: 114005
A5: 39155 | B5: 39155:CORPORATE & SOCIAL RESPONSIBILITY | C5: =VLOOKUP(A5,'Cost Center'!A:C,3,FALSE) -> C200550 | D5: C200550 | E5: Corporate | F5: 39155
A6: 1013500 | B6: 1013500:WASHINGTON, DC FACILITY | C6: =VLOOKUP(A6,'Cost Center'!A:C,3,FALSE) -> C500517 | D6: C500517 | E6: Corporate | F6: 1013500
A7: 3200493 | B7: 3200493:WOODBURY MN FACILITY | C7: =VLOOKUP(A7,'Cost Center'!A:C,3,FALSE) -> C500518 | D7: C500518 | E7: Corporate | F7: 3200493
A8: 114300 | B8: 114300:NY OFFICE SERVICES | C8: =VLOOKUP(A8,'Cost Center'!A:C,3,FALSE) -> C500105 | D8: C500105 | E8: Corporate | F8: 114300
A9: 114450 | B9: 114450:INC NY CORPORATE FACILITY | C9: =VLOOKUP(A9,'Cost Center'!A:C,3,FALSE) -> C500519 | D9: C500519 | E9: Corporate | F9: 114450
A10: 8310310 | B10: 8310310:MFD AIZ | C10: =VLOOKUP(A10,'Cost Center'!A:C,3,FALSE) -> C200116 | D10: C200116 | E10: Corporate | F10: 8310310
A11: 114425 | B11: 114425:ATLANTA DATA CENTER | C11: =VLOOKUP(A11,'Cost Center'!A:C,3,FALSE) -> C500522 | D11: C500522 | E11: Corporate | F11: 114425
A12: 113035 | B12: 113035:PROCUREMENT OUTSOURCING | C12: =VLOOKUP(A12,'Cost Center'!A:C,3,FALSE) -> C200201 | D12: C200201 | E12: Corporate | F12: 113035
A13: 113041 | B13: 113041:VENDOR RISK & ANALYTICS | C13: =VLOOKUP(A13,'Cost Center'!A:C,3,FALSE) -> C200205 | D13: C200205 | E13: Corporate | F13: 113041
... A59: 113010 | B59: 113010:OFFICE OF CEO | C59: =VLOOKUP(A59,'Cost Center'!A:C,3,FALSE) -> C030101 | D59: C030101 | E59: Corporate | F59: 113010
A60: 304000 | B60: 0304000:ACTUARIAL PRENEED | C60: =VLOOKUP(A60,'Cost Center'!A:C,3,FALSE) -> #N/A | D60: #N/A | E60: Corporate | F60: 304000
A61: 113002 | B61: 113002:NETWORK OPERATIONS | C61: =VLOOKUP(A61,'Cost Center'!A:C,3,FALSE) -> C010902 | D61: C010902 | E61: Corporate | F61: 113002
A62: 150600 | B62: 150600:AAM MORTGAGES | C62: =VLOOKUP(A62,'Cost Center'!A:C,3,FALSE) -> #N/A | D62: C900000 | E62: Corporate | F62: 150600
A63: 150700 | B63: 150700:AAM EQUITY REAL ESTATE | C63: =VLOOKUP(A63,'Cost Center'!A:C,3,FALSE) -> C010702 | D63: C010702 | E63: Corporate | F63: 150700
A64: 150800 | B64: 150800:AAM FIXED INCOME | C64: =VLOOKUP(A64,'Cost Center'!A:C,3,FALSE) -> C010701 | D64: C010701 | E64: Corporate | F64: 150800
A65: 150950 | B65: 150950:AIM CORP | C65: =VLOOKUP(A65,'Cost Center'!A:C,3,FALSE) -> C010750 | D65: C010750 | E65: Corporate | F65: 150950
A66: 150952 | B66: 150952:AIM FUND | C66: =VLOOKUP(A66,'Cost Center'!A:C,3,FALSE) -> #N/A | D66: C900000 | E66: Corporate | F66: 150952
A67: 113049 | B67: 113049:Accounting & Finance Services - A&FS | C67: =VLOOKUP(A67,'Cost Center'!A:C,3,FALSE) -> C010121 | D67: C010121 | E67: Corporate | F67: 113049
A68: 113051 | B68: 113051:A&FS ONE TIME COSTS | C68: =VLOOKUP(A68,'Cost Center'!A:C,3,FALSE) -> C010123 | D68: C010123 | E68: Corporate | F68: 113051
A69: 113052 | B69: 113052:A&FS OPERATIONS | C69: =VLOOKUP(A69,'Cost Center'!A:C,3,FALSE) -> C010124 | D69: C010124 | E69: Corporate | F69: 113052
A70: 113053 | B70: 113053:A&FS CASH APPLICATIONS | C70: =VLOOKUP(A70,'Cost Center'!A:C,3,FALSE) -> C010122 | D70: C010122 | E70: Corporate | F70: 113053
A71: 113054 | B71: 113054:AFS RECON COE | C71: =VLOOKUP(A71,'Cost Center'!A:C,3,FALSE) -> C010127 | D71: C010127 | E71: Corporate | F71: 113054
A72: 113056 | B72: 113056:A&FS OUTSOURCING | C72: =VLOOKUP(A72,'Cost Center'!A:C,3,FALSE) -> C010126 | D72: C010126 | E72: Corporate | F72: 113056
... A87: 54320 | B87: 54320:ACTUARIAL DATA OPS & TECHNOLOGY | C87: =VLOOKUP(A87,'Cost Center'!A:C,3,FALSE) -> C010205 | D87: C010205 | E87: Corporate | F87: 54320
A88: U9913 | B88: U9913:ACTUARIAL GLOBAL AUTO | C88: =VLOOKUP(A88,'Cost Center'!A:C,3,FALSE) -> C010215 | D88: C010215 | E88: Corporate | F88: U9913
A89: 113020 | B89: 113020:CAPITAL AND FINANCIAL RATINGS | C89: =VLOOKUP(A89,'Cost Center'!A:C,3,FALSE) -> C010801 | D89: C010801 | E89: Corporate | F89: 113020
A90: 113240 | B90: 113240:TREASURY | C90: =VLOOKUP(A90,'Cost Center'!A:C,3,FALSE) -> C010800 | D90: C010800 | E90: Corporate | F90: 113240
A91: 150400 | B91: 150400:REVOLVER ISSUANCE COSTS | C91: =VLOOKUP(A91,'Cost Center'!A:C,3,FALSE) -> C010890 | D91: C010890 | E91: Corporate | F91: 150400
A92: 17202 | B92: 17202:TREASURY MANAGEMENT | C92: =VLOOKUP(A92,'Cost Center'!A:C,3,FALSE) -> C100601 | D92: C100601 | E92: Corporate | F92: 17202
A93: 122000 | B93: 122000:Global Risk Modeling and Insurance Purchasing | C93: =VLOOKUP(A93,'Cost Center'!A:C,3,FALSE) -> C010805 | D93: C010805 | E93: Corporate | F93: 122000
A94: 115003 | B94: 115003:RAS AEB | C94: =VLOOKUP(A94,'Cost Center'!A:C,3,FALSE) -> #N/A | D94: C900000 | E94: Corporate | F94: 115003
A95: 115027 | B95: 115027:RAS QA TRAINING | C95: =VLOOKUP(A95,'Cost Center'!A:C,3,FALSE) -> #N/A | D95: C900000 | E95: Corporate | F95: 115027
A96: 113040 | B96: 113040:OFFICE OF CFO | C96: =VLOOKUP(A96,'Cost Center'!A:C,3,FALSE) -> C010000 | D96: C010000 | E96: Corporate | F96: 113040
A97: 10300 | B97: 10300:MIAMI CORPORATE FP AND A | C97: =VLOOKUP(A97,'Cost Center'!A:C,3,FALSE) -> #N/A | D97: #N/A | E97: Corporate | F97: 10300
A98: 113100 | B98: 113100:CORPORATE FP AND A | C98: =VLOOKUP(A98,'Cost Center'!A:C,3,FALSE) -> C010410 | D98: C010410 | E98: Corporate | F98: 113100
A99: 113232 | B99: 113232:IT FINANCE EXECUTIVE | C99: =VLOOKUP(A99,'Cost Center'!A:C,3,FALSE) -> C010415 | D99: C010415 | E99: Corporate | F99: 113232
A100: 113233 | B100: 113233:ENTERPRISE FP AND A | C100: =VLOOKUP(A100,'Cost Center'!A:C,3,FALSE) -> C010401 | D100: C010401 | E100: Corporate | F100: 113233
A101: 113234 | B101: 113234:IT FINANCE ANALYSIS MIAMI | C101: =VLOOKUP(A101,'Cost Center'!A:C,3,FALSE) -> CI10417 | D101: CI10417 | E101: Corporate | F101: 113234
A102: 115000 | B102: 115000:IAS CORPORATE | C102: =VLOOKUP(A102,'Cost Center'!A:C,3,FALSE) -> C010301 | D102: C010301 | E102: Corporate | F102: 115000
A103: 115001 | B103: 115001:IAS GENERAL | C103: =VLOOKUP(A103,'Cost Center'!A:C,3,FALSE) -> C010310 | D103: C010310 | E103: Corporate | F103: 115001
A104: 115002 | B104: 115002:IAS | C104: =VLOOKUP(A104,'Cost Center'!A:C,3,FALSE) -> C010305 | D104: C010305 | E104: Corporate | F104: 115002
A105: 115051 | B105: 115051:RAS AS GENERAL AUDITS | C105: =VLOOKUP(A105,'Cost Center'!A:C,3,FALSE) -> #N/A | D105: C900000 | E105: Corporate | F105: 115051
A106: 113220 | B106: 113220:CORPORATE TAX | C106: =VLOOKUP(A106,'Cost Center'!A:C,3,FALSE) -> C010501 | D106: C010501 | E106: Corporate | F106: 113220
A107: 113223 | B107: 113223:MKE TAX DEPARTMENT | C107: =VLOOKUP(A107,'Cost Center'!A:C,3,FALSE) -> CI10508 | D107: CI10508 | E107: Corporate | F107: 113223
A108: 118120 | B108: 118120:TWG TAX | C108: =VLOOKUP(A108,'Cost Center'!A:C,3,FALSE) -> CI10509 | D108: CI10509 | E108: Corporate | F108: 118120
A109: 13400 | B109: 13400:TREASURY TAX | C109: =VLOOKUP(A109,'Cost Center'!A:C,3,FALSE) -> CI10510 | D109: CI10510 | E109: Corporate | F109: 13400
... A112: 115005 | B112: 115005:RAS IT | C112: =VLOOKUP(A112,'Cost Center'!A:C,3,FALSE) -> C020990 | D112: C020990 | E112: Corporate | F112: 115005
A113: 115008 | B113: 115008:RAS CORP | C113: =VLOOKUP(A113,'Cost Center'!A:C,3,FALSE) -> #N/A | D113: #N/A | E113: Corporate | F113: 115008
A114: 10070 | B114: 10070:PRIVACY OPERATIONS | C114: =VLOOKUP(A114,'Cost Center'!A:C,3,FALSE) -> C020601 | D114: C020601 | E114: Corporate | F114: 10070
A115: 10487 | B115: 10487:STATE EXAMS FEES | C115: =VLOOKUP(A115,'Cost Center'!A:C,3,FALSE) -> C703004 | D115: C703004 | E115: Corporate | F115: 10487
A116: 113289 | B116: 113289:EXAM OPERATIONS | C116: =VLOOKUP(A116,'Cost Center'!A:C,3,FALSE) -> #N/A | D116: C900000 | E116: Corporate | F116: 113289
A117: 113290 | B117: 113290:COMPLIANCE ENTERPRISE EXPENSES | C117: =VLOOKUP(A117,'Cost Center'!A:C,3,FALSE) -> C020402 | D117: C020402 | E117: Corporate | F117: 113290
A118: 113291 | B118: 113291:ETHICS | C118: =VLOOKUP(A118,'Cost Center'!A:C,3,FALSE) -> C020425 | D118: C020425 | E118: Corporate | F118: 113291
A119: 113292 | B119: 113292:CORPORATE COMPLIANCE OPERATIONS | C119: =VLOOKUP(A119,'Cost Center'!A:C,3,FALSE) -> CI20402 | D119: CI20402 | E119: Corporate | F119: 113292
A120: 113293 | B120: 113293:BU COMPLIANCE GLOBAL LIFESTYLE | C120: =VLOOKUP(A120,'Cost Center'!A:C,3,FALSE) -> #N/A | D120: C900000 | E120: Corporate | F120: 113293
A121: 113294 | B121: 113294:BU COMPLIANCE GLOBAL HOUSING | C121: =VLOOKUP(A121,'Cost Center'!A:C,3,FALSE) -> #N/A | D121: C900000 | E121: Corporate | F121: 113294
A122: 20950 | B122: 20950:USLIC COMPLIANCE | C122: =VLOOKUP(A122,'Cost Center'!A:C,3,FALSE) -> C703005 | D122: C703005 | E122: Corporate | F122: 20950
A123: 21500 | B123: 21500:REGISTRATION OPERATIONS | C123: =VLOOKUP(A123,'Cost Center'!A:C,3,FALSE) -> C020801 | D123: C020801 | E123: Corporate | F123: 21500
A124: 51915 | B124: 51915:STATE FILING FEES | C124: =VLOOKUP(A124,'Cost Center'!A:C,3,FALSE) -> C703006 | D124: C703006 | E124: Corporate | F124: 51915
A125: 51950 | B125: 51950:COMPLIANCE TECH | C125: =VLOOKUP(A125,'Cost Center'!A:C,3,FALSE) -> C020415 | D125: C020415 | E125: Corporate | F125: 51950
... A137: 113030 | B137: 113030:GOVERNMENT RELATIONS | C137: =VLOOKUP(A137,'Cost Center'!A:C,3,FALSE) -> C020501 | D137: C020501 | E137: Corporate | F137: 113030
A138: 51105 | B138: 51105:LEGAL COMPLIANCE | C138: =VLOOKUP(A138,'Cost Center'!A:C,3,FALSE) -> #N/A | D138: #N/A | E138: Corporate | F138: 51105
A139: 51800 | B139: 51800:GOVERNMENT RELATIONS | C139: =VLOOKUP(A139,'Cost Center'!A:C,3,FALSE) -> C020503 | D139: C020503 | E139: Corporate | F139: 51800
A140: 51953 | B140: 51953:AVIP CLUB | C140: =VLOOKUP(A140,'Cost Center'!A:C,3,FALSE) -> #N/A | D140: C900000 | E140: Corporate | F140: 51953
A141: 113060 | B141: 113060:OFFICE OF CHIEF LEGAL OFFICER | C141: =VLOOKUP(A141,'Cost Center'!A:C,3,FALSE) -> C020201 | D141: C020201 | E141: Corporate | F141: 113060
A142: 113250 | B142: 113250:LEGAL | C142: =VLOOKUP(A142,'Cost Center'!A:C,3,FALSE) -> C020202 | D142: C020202 | E142: Corporate | F142: 113250
A143: 113260 | B143: 113260:SHAREHOLDER MEETING | C143: =VLOOKUP(A143,'Cost Center'!A:C,3,FALSE) -> C030205 | D143: C030205 | E143: Corporate | F143: 113260
A144: 113270 | B144: 113270:BOARD OF DIRECTORS | C144: =VLOOKUP(A144,'Cost Center'!A:C,3,FALSE) -> C030151 | D144: C030151 | E144: Corporate | F144: 113270
A145: 113295 | B145: 113295:LEGAL OPERATIONS | C145: =VLOOKUP(A145,'Cost Center'!A:C,3,FALSE) -> CI20223 | D145: CI20223 | E145: Corporate | F145: 113295
A146: 53501 | B146: 53501:CORPORATE LITIGATION FEES | C146: =VLOOKUP(A146,'Cost Center'!A:C,3,FALSE) -> C020901 | D146: C020901 | E146: Corporate | F146: 53501
A147: 10809 | B147: 10809:STATE FILINGS OPERATIONS | C147: =VLOOKUP(A147,'Cost Center'!A:C,3,FALSE) -> C040405 | D147: C040405 | E147: Corporate | F147: 10809
A148: 51502 | B148: 51502:COMPLIANCE COMMUNICATIONS OPERATIONS | C148: =VLOOKUP(A148,'Cost Center'!A:C,3,FALSE) -> C040401 | D148: C040401 | E148: Corporate | F148: 51502
A149: 51900 | B149: 51900:LICENSING OPERATIONS | C149: =VLOOKUP(A149,'Cost Center'!A:C,3,FALSE) -> C040330 | D149: C040330 | E149: Corporate | F149: 51900
A150: 10256 | B150: 10256:LENDING SOLUTIONS CX | C150: =VLOOKUP(A150,'Cost Center'!A:C,3,FALSE) -> C040115 | D150: C040115 | E150: Corporate | F150: 10256
... A171: 72839 | B171: 72839:REPORT ADMINISTRATION | C171: =VLOOKUP(A171,'Cost Center'!A:C,3,FALSE) -> C040601 | D171: C040601 | E171: Corporate | F171: 72839
A172: WH590 | B172: WH590:TN DATA ANALYTICS TIU | C172: =VLOOKUP(A172,'Cost Center'!A:C,3,FALSE) -> C040020 | D172: C040020 | E172: Corporate | F172: WH590
A173: 113500 | B173: 113500:Chief Operating Officer | C173: =VLOOKUP(A173,'Cost Center'!A:C,3,FALSE) -> C030115 | D173: C030115 | E173: Corporate | F173: 113500
A174: 113510 | B174: 113510:OPERATIONS TRANSFORMATION | C174: =VLOOKUP(A174,'Cost Center'!A:C,3,FALSE) -> C040410 | D174: C040410 | E174: Corporate | F174: 113510
A175: 113200 | B175: 113200:RISK MANAGEMENT | C175: =VLOOKUP(A175,'Cost Center'!A:C,3,FALSE) -> C042002 | D175: C042002 | E175: Corporate | F175: 113200
A176: 113600 | B176: 113600:Chief Risk Officer | C176: =VLOOKUP(A176,'Cost Center'!A:C,3,FALSE) -> C030120 | D176: C030120 | E176: Corporate | F176: 113600
A177: 113032 | B177: 113032:GLOBAL SECURITY SERVICES | C177: =VLOOKUP(A177,'Cost Center'!A:C,3,FALSE) -> C042005 | D177: C042005 | E177: Corporate | F177: 113032
A178: 113607 | B178: 113607:DR BUSINESS CONTINUITY | C178: =VLOOKUP(A178,'Cost Center'!A:C,3,FALSE) -> C042030 | D178: C042030 | E178: Corporate | F178: 113607
A179: 113604 | B179: 113604:FINANCIAL RISK | C179: =VLOOKUP(A179,'Cost Center'!A:C,3,FALSE) -> C042020 | D179: C042020 | E179: Corporate | F179: 113604
A180: 113605 | B180: 113605:LS RISK MGMT | C180: =VLOOKUP(A180,'Cost Center'!A:C,3,FALSE) -> C042025 | D180: C042025 | E180: Corporate | F180: 113605
A181: 113601 | B181: 113601:OPERATIONAL RISK | C181: =VLOOKUP(A181,'Cost Center'!A:C,3,FALSE) -> C042010 | D181: C042010 | E181: Corporate | F181: 113601
A182: 113602 | B182: 113602:BUSINESS RISK | C182: =VLOOKUP(A182,'Cost Center'!A:C,3,FALSE) -> C042015 | D182: C042015 | E182: Corporate | F182: 113602
A183: 113608 | B183: 113608:LFS AUTO RISK MGMT | C183: =VLOOKUP(A183,'Cost Center'!A:C,3,FALSE) -> #N/A | D183: C900000 | E183: Corporate | F183: 113608
A184: 121030 | B184: 121030:BUSINESS STRATEGY | C184: =VLOOKUP(A184,'Cost Center'!A:C,3,FALSE) -> C043020 | D184: C043020 | E184: Corporate | F184: 121030
A185: 141000 | B185: 141000:LIFESTYLE AND INTERNATIONAL STRATEGY | C185: =VLOOKUP(A185,'Cost Center'!A:C,3,FALSE) -> #N/A | D185: #N/A | E185: Corporate | F185: 141000
A186: 113520 | B186: 113520:ENT TRANSFM CENTER OF EXCELLENCE | C186: =VLOOKUP(A186,'Cost Center'!A:C,3,FALSE) -> C043005 | D186: C043005 | E186: Corporate | F186: 113520
A187: 113070 | B187: 113070:OFFICE OF CSO | C187: =VLOOKUP(A187,'Cost Center'!A:C,3,FALSE) -> C030125 | D187: C030125 | E187: Corporate | F187: 113070
A188: 121010 | B188: 121010:CONSUMER INSIGHTS | C188: =VLOOKUP(A188,'Cost Center'!A:C,3,FALSE) -> C043010 | D188: C043010 | E188: Corporate | F188: 121010
A189: 121020 | B189: 121020:GROWTH & INNOVATION | C189: =VLOOKUP(A189,'Cost Center'!A:C,3,FALSE) -> C043015 | D189: C043015 | E189: Corporate | F189: 121020
A190: 190110 | B190: 190110:ENTERPRISE STRATEGY | C190: =VLOOKUP(A190,'Cost Center'!A:C,3,FALSE) -> C043035 | D190: C043035 | E190: Corporate | F190: 190110
A191: 113001 | B191: 113001:MERGERS AND ACQUISITIONS | C191: =VLOOKUP(A191,'Cost Center'!A:C,3,FALSE) -> C043001 | D191: C043001 | E191: Corporate | F191: 113001
A192: 190120 | B192: 190120:MERGERS AND ACQUISITIONS SOURCING | C192: =VLOOKUP(A192,'Cost Center'!A:C,3,FALSE) -> C030989 | D192: C030989 | E192: Corporate | F192: 190120
...

Sheet Email II
